[[{"type":"word","word":"The","hasSynonym":false},{"type":"word","word":"strange","hasSynonym":false},{"type":"word","word":"driver","hasSynonym":false},{"type":"word","word":"evidently","hasSynonym":false},{"type":"word","word":"heard","hasSynonym":false},{"type":"word","word":"the","hasSynonym":false},{"type":"word","word":"words,","hasSynonym":false},{"type":"word","word":"for","hasSynonym":false},{"type":"word","word":"he","hasSynonym":false},{"type":"word","word":"looked","hasSynonym":false},{"type":"word","word":"up","hasSynonym":false},{"type":"word","word":"with","hasSynonym":false},{"type":"word","word":"a","hasSynonym":false},{"type":"word","word":"gleaming","synonym":"shine","hasSynonym":true},{"type":"word","word":"smile.","hasSynonym":false},{"type":"word","word":"The","hasSynonym":false},{"type":"word","word":"passenger","hasSynonym":false},{"type":"word","word":"turned","hasSynonym":false},{"type":"word","word":"his","hasSynonym":false},{"type":"word","word":"face","hasSynonym":false},{"type":"word","word":"away,","hasSynonym":false},{"type":"word","word":"at","hasSynonym":false},{"type":"word","word":"the","hasSynonym":false},{"type":"word","word":"same","hasSynonym":false},{"type":"word","word":"time","hasSynonym":false},{"type":"word","word":"putting","hasSynonym":false},{"type":"word","word":"out","hasSynonym":false},{"type":"word","word":"his","hasSynonym":false},{"type":"word","word":"two","hasSynonym":false},{"type":"word","word":"fingers","hasSynonym":false},{"type":"word","word":"and","hasSynonym":false},{"type":"word","word":"crossing","synonym":"to make the sign of the cross","hasSynonym":true},{"type":"word","word":"himself.","hasSynonym":false},{"type":"word","word":"“Give","hasSynonym":false},{"type":"word","word":"me","hasSynonym":false},{"type":"word","word":"the","hasSynonym":false},{"type":"word","word":"Herr’s","hasSynonym":false},{"type":"word","word":"luggage,”","synonym":"suitcases","hasSynonym":true},{"type":"word","word":"said","hasSynonym":false},{"type":"word","word":"the","hasSynonym":false},{"type":"word","word":"driver;","hasSynonym":false},{"type":"word","word":"and","hasSynonym":false},{"type":"word","word":"with","hasSynonym":false},{"type":"word","word":"exceeding","hasSynonym":false},{"type":"word","word":"alacrity","synonym":"readiness, quickness","hasSynonym":true},{"type":"word","word":"my","hasSynonym":false},{"type":"word","word":"bags","hasSynonym":false},{"type":"word","word":"were","hasSynonym":false},{"type":"word","word":"handed","hasSynonym":false},{"type":"word","word":"out","hasSynonym":false},{"type":"word","word":"and","hasSynonym":false},{"type":"word","word":"put","hasSynonym":false},{"type":"word","word":"in","hasSynonym":false},{"type":"word","word":"the","hasSynonym":false},{"type":"word","word":"calèche.","hasSynonym":false},{"type":"word","word":"Then","hasSynonym":false},{"type":"word","word":"I","hasSynonym":false},{"type":"word","word":"descended","hasSynonym":false},{"type":"word","word":"from","hasSynonym":false},{"type":"word","word":"the","hasSynonym":false},{"type":"word","word":"side","hasSynonym":false},{"type":"word","word":"of","hasSynonym":false},{"type":"word","word":"the","hasSynonym":false},{"type":"word","word":"coach,","synonym":"a large, horse-drawn, four-wheeled carriage, usually enclosed","hasSynonym":true},{"type":"word","word":"as","hasSynonym":false},{"type":"word","word":"the","hasSynonym":false},{"type":"word","word":"calèche","hasSynonym":false},{"type":"word","word":"was","hasSynonym":false},{"type":"word","word":"close","hasSynonym":false},{"type":"word","word":"alongside,","hasSynonym":false},{"type":"word","word":"the","hasSynonym":false},{"type":"word","word":"driver","hasSynonym":false},{"type":"word","word":"helping","hasSynonym":false},{"type":"word","word":"me","hasSynonym":false},{"type":"word","word":"with","hasSynonym":false},{"type":"word","word":"a","hasSynonym":false},{"type":"word","word":"hand","hasSynonym":false},{"type":"word","word":"which","hasSynonym":false},{"type":"word","word":"caught","synonym":"past verb of catch","hasSynonym":true},{"type":"word","word":"my","hasSynonym":false},{"type":"word","word":"arm","hasSynonym":false},{"type":"word","word":"in","hasSynonym":false},{"type":"word","word":"a","hasSynonym":false},{"type":"word","word":"grip","synonym":"fascinate, hold","hasSynonym":true},{"type":"word","word":"of","hasSynonym":false},{"type":"word","word":"steel;","synonym":"metal","hasSynonym":true},{"type":"word","word":"his","hasSynonym":false},{"type":"word","word":"strength","hasSynonym":false},{"type":"word","word":"must","hasSynonym":false},{"type":"word","word":"have","hasSynonym":false},{"type":"word","word":"been","hasSynonym":false},{"type":"word","word":"prodigious.","hasSynonym":false},{"type":"word","word":"Without","hasSynonym":false},{"type":"word","word":"a","hasSynonym":false},{"type":"word","word":"word","hasSynonym":false},{"type":"word","word":"he","hasSynonym":false},{"type":"word","word":"shook","hasSynonym":false},{"type":"word","word":"his","hasSynonym":false},{"type":"word","word":"reins,","hasSynonym":false},{"type":"word","word":"the","hasSynonym":false},{"type":"word","word":"horses","hasSynonym":false},{"type":"word","word":"turned,","hasSynonym":false},{"type":"word","word":"and","hasSynonym":false},{"type":"word","word":"we","hasSynonym":false},{"type":"word","word":"swept","synonym":"turned, rounded, go around","hasSynonym":true},{"type":"word","word":"into","hasSynonym":false},{"type":"word","word":"the","hasSynonym":false},{"type":"word","word":"darkness","hasSynonym":false},{"type":"word","word":"of","hasSynonym":false},{"type":"word","word":"the","hasSynonym":false},{"type":"word","word":"Pass.","hasSynonym":false},{"type":"word","word":"As","hasSynonym":false},{"type":"word","word":"I","hasSynonym":false},{"type":"word","word":"looked","hasSynonym":false},{"type":"word","word":"back","hasSynonym":false},{"type":"word","word":"I","hasSynonym":false},{"type":"word","word":"saw","hasSynonym":false},{"type":"word","word":"the","hasSynonym":false},{"type":"word","word":"steam","hasSynonym":false},{"type":"word","word":"from","hasSynonym":false},{"type":"word","word":"the","hasSynonym":false},{"type":"word","word":"horses","hasSynonym":false},{"type":"word","word":"of","hasSynonym":false},{"type":"word","word":"the","hasSynonym":false},{"type":"word","word":"coach","synonym":"a large, horse-drawn, four-wheeled carriage, usually enclosed","hasSynonym":true},{"type":"word","word":"by","hasSynonym":false},{"type":"word","word":"the","hasSynonym":false},{"type":"word","word":"light","hasSynonym":false},{"type":"word","word":"of","hasSynonym":false},{"type":"word","word":"the","hasSynonym":false},{"type":"word","word":"lamps,","hasSynonym":false},{"type":"word","word":"and","hasSynonym":false},{"type":"word","word":"projected","hasSynonym":false},{"type":"word","word":"against","hasSynonym":false},{"type":"word","word":"it","hasSynonym":false},{"type":"word","word":"the","hasSynonym":false},{"type":"word","word":"figures","hasSynonym":false},{"type":"word","word":"of","hasSynonym":false},{"type":"word","word":"my","hasSynonym":false},{"type":"word","word":"late","hasSynonym":false},{"type":"word","word":"companions","hasSynonym":false},{"type":"word","word":"crossing","synonym":"to make the sign of the cross","hasSynonym":true},{"type":"word","word":"themselves.","hasSynonym":false},{"type":"word","word":"Then","hasSynonym":false},{"type":"word","word":"the","hasSynonym":false},{"type":"word","word":"driver","hasSynonym":false},{"type":"word","word":"cracked","synonym":"fissured, split, fractured","hasSynonym":true},{"type":"word","word":"his","hasSynonym":false},{"type":"word","word":"whip","hasSynonym":false},{"type":"word","word":"and","hasSynonym":false},{"type":"word","word":"called","hasSynonym":false},{"type":"word","word":"to","hasSynonym":false},{"type":"word","word":"his","hasSynonym":false},{"type":"word","word":"horses,","hasSynonym":false},{"type":"word","word":"and","hasSynonym":false},{"type":"word","word":"off","hasSynonym":false},{"type":"word","word":"they","hasSynonym":false},{"type":"word","word":"swept","synonym":"turned, rounded, go around","hasSynonym":true},{"type":"word","word":"on","hasSynonym":false},{"type":"word","word":"their","hasSynonym":false},{"type":"word","word":"way","hasSynonym":false},{"type":"word","word":"to","hasSynonym":false},{"type":"word","word":"Bukovina.","hasSynonym":false},{"type":"word","word":"As","hasSynonym":false},{"type":"word","word":"they","hasSynonym":false},{"type":"word","word":"sank","synonym":"fall","hasSynonym":true},{"type":"word","word":"into","hasSynonym":false},{"type":"word","word":"the","hasSynonym":false},{"type":"word","word":"darkness","hasSynonym":false},{"type":"word","word":"I","hasSynonym":false},{"type":"word","word":"felt","hasSynonym":false},{"type":"word","word":"a","hasSynonym":false},{"type":"word","word":"strange","hasSynonym":false},{"type":"word","word":"chill,","synonym":"coldness","hasSynonym":true},{"type":"word","word":"and","hasSynonym":false},{"type":"word","word":"a","hasSynonym":false},{"type":"word","word":"lonely","hasSynonym":false},{"type":"word","word":"feeling","hasSynonym":false},{"type":"word","word":"came","hasSynonym":false},{"type":"word","word":"over","hasSynonym":false},{"type":"word","word":"me;","hasSynonym":false},{"type":"word","word":"but","hasSynonym":false},{"type":"word","word":"a","hasSynonym":false},{"type":"word","word":"cloak","hasSynonym":false},{"type":"word","word":"was","hasSynonym":false},{"type":"word","word":"thrown","hasSynonym":false},{"type":"word","word":"over","hasSynonym":false},{"type":"word","word":"my","hasSynonym":false},{"type":"word","word":"shoulders,","hasSynonym":false},{"type":"word","word":"and","hasSynonym":false},{"type":"word","word":"a","hasSynonym":false},{"type":"word","word":"rug","synonym":"carpet","hasSynonym":true},{"type":"word","word":"across","hasSynonym":false},{"type":"word","word":"my","hasSynonym":false},{"type":"word","word":"knees,","hasSynonym":false},{"type":"word","word":"and","hasSynonym":false},{"type":"word","word":"the","hasSynonym":false},{"type":"word","word":"driver","hasSynonym":false},{"type":"word","word":"said","hasSynonym":false},{"type":"word","word":"in","hasSynonym":false},{"type":"word","word":"excellent","hasSynonym":false},{"type":"word","word":"German:—","hasSynonym":false}],[{"type":"word","word":"“The","hasSynonym":false},{"type":"word","word":"night","hasSynonym":false},{"type":"word","word":"is","hasSynonym":false},{"type":"word","word":"chill,","synonym":"coldness","hasSynonym":true},{"type":"word","word":"mein","hasSynonym":false},{"type":"word","word":"Herr,","hasSynonym":false},{"type":"word","word":"and","hasSynonym":false},{"type":"word","word":"my","hasSynonym":false},{"type":"word","word":"master","hasSynonym":false},{"type":"word","word":"the","hasSynonym":false},{"type":"word","word":"Count","hasSynonym":false},{"type":"word","word":"bade","hasSynonym":false},{"type":"word","word":"me","hasSynonym":false},{"type":"word","word":"take","hasSynonym":false},{"type":"word","word":"all","hasSynonym":false},{"type":"word","word":"care","hasSynonym":false},{"type":"word","word":"of","hasSynonym":false},{"type":"word","word":"you.","hasSynonym":false},{"type":"word","word":"There","hasSynonym":false},{"type":"word","word":"is","hasSynonym":false},{"type":"word","word":"a","hasSynonym":false},{"type":"word","word":"flask","synonym":"bottle","hasSynonym":true},{"type":"word","word":"of","hasSynonym":false},{"type":"word","word":"slivovitz","hasSynonym":false},{"type":"word","word":"(the","hasSynonym":false},{"type":"word","word":"plum","synonym":"purple fruit","hasSynonym":true},{"type":"word","word":"brandy","hasSynonym":false},{"type":"word","word":"of","hasSynonym":false},{"type":"word","word":"the","hasSynonym":false},{"type":"word","word":"country)","hasSynonym":false},{"type":"word","word":"underneath","synonym":"below","hasSynonym":true},{"type":"word","word":"the","hasSynonym":false},{"type":"word","word":"seat,","hasSynonym":false},{"type":"word","word":"if","hasSynonym":false},{"type":"word","word":"you","hasSynonym":false},{"type":"word","word":"should","hasSynonym":false},{"type":"word","word":"require","hasSynonym":false},{"type":"word","word":"it.”","hasSynonym":false},{"type":"word","word":"I","hasSynonym":false},{"type":"word","word":"did","hasSynonym":false},{"type":"word","word":"not","hasSynonym":false},{"type":"word","word":"take","hasSynonym":false},{"type":"word","word":"any,","hasSynonym":false},{"type":"word","word":"but","hasSynonym":false},{"type":"word","word":"it","hasSynonym":false},{"type":"word","word":"was","hasSynonym":false},{"type":"word","word":"a","hasSynonym":false},{"type":"word","word":"comfort","hasSynonym":false},{"type":"word","word":"to","hasSynonym":false},{"type":"word","word":"know","hasSynonym":false},{"type":"word","word":"it","hasSynonym":false},{"type":"word","word":"was","hasSynonym":false},{"type":"word","word":"there","hasSynonym":false},{"type":"word","word":"all","hasSynonym":false},{"type":"word","word":"the","hasSynonym":false},{"type":"word","word":"same.","hasSynonym":false},{"type":"word","word":"I","hasSynonym":false},{"type":"word","word":"felt","hasSynonym":false},{"type":"word","word":"a","hasSynonym":false},{"type":"word","word":"little","hasSynonym":false},{"type":"word","word":"strangely,","hasSynonym":false},{"type":"word","word":"and","hasSynonym":false},{"type":"word","word":"not","hasSynonym":false},{"type":"word","word":"a","hasSynonym":false},{"type":"word","word":"little","hasSynonym":false},{"type":"word","word":"frightened.","synonym":"afraid, scared","hasSynonym":true},{"type":"word","word":"I","hasSynonym":false},{"type":"word","word":"think","hasSynonym":false},{"type":"word","word":"had","hasSynonym":false},{"type":"word","word":"there","hasSynonym":false},{"type":"word","word":"been","hasSynonym":false},{"type":"word","word":"any","hasSynonym":false},{"type":"word","word":"alternative","hasSynonym":false},{"type":"word","word":"I","hasSynonym":false},{"type":"word","word":"should","hasSynonym":false},{"type":"word","word":"have","hasSynonym":false},{"type":"word","word":"taken","hasSynonym":false},{"type":"word","word":"it,","hasSynonym":false},{"type":"word","word":"instead","hasSynonym":false},{"type":"word","word":"of","hasSynonym":false},{"type":"word","word":"prosecuting","synonym":"continuing on","hasSynonym":true},{"type":"word","word":"that","hasSynonym":false},{"type":"word","word":"unknown","hasSynonym":false},{"type":"word","word":"night","hasSynonym":false},{"type":"word","word":"journey.","hasSynonym":false},{"type":"word","word":"The","hasSynonym":false},{"type":"word","word":"carriage","hasSynonym":false},{"type":"word","word":"went","hasSynonym":false},{"type":"word","word":"at","hasSynonym":false},{"type":"word","word":"a","hasSynonym":false},{"type":"word","word":"hard","hasSynonym":false},{"type":"word","word":"pace","hasSynonym":false},{"type":"word","word":"straight","hasSynonym":false},{"type":"word","word":"along,","hasSynonym":false},{"type":"word","word":"then","hasSynonym":false},{"type":"word","word":"we","hasSynonym":false},{"type":"word","word":"made","hasSynonym":false},{"type":"word","word":"a","hasSynonym":false},{"type":"word","word":"complete","hasSynonym":false},{"type":"word","word":"turn","hasSynonym":false},{"type":"word","word":"and","hasSynonym":false},{"type":"word","word":"went","hasSynonym":false},{"type":"word","word":"along","hasSynonym":false},{"type":"word","word":"another","hasSynonym":false},{"type":"word","word":"straight","hasSynonym":false},{"type":"word","word":"road.","hasSynonym":false},{"type":"word","word":"It","hasSynonym":false},{"type":"word","word":"seemed","synonym":"appeared to be, looked to be","hasSynonym":true},{"type":"word","word":"to","hasSynonym":false},{"type":"word","word":"me","hasSynonym":false},{"type":"word","word":"that","hasSynonym":false},{"type":"word","word":"we","hasSynonym":false},{"type":"word","word":"were","hasSynonym":false},{"type":"word","word":"simply","hasSynonym":false},{"type":"word","word":"going","hasSynonym":false},{"type":"word","word":"over","hasSynonym":false},{"type":"word","word":"and","hasSynonym":false},{"type":"word","word":"over","hasSynonym":false},{"type":"word","word":"the","hasSynonym":false},{"type":"word","word":"same","hasSynonym":false},{"type":"word","word":"ground","hasSynonym":false},{"type":"word","word":"again;","hasSynonym":false},{"type":"word","word":"and","hasSynonym":false},{"type":"word","word":"so","hasSynonym":false},{"type":"word","word":"I","hasSynonym":false},{"type":"word","word":"took","hasSynonym":false},{"type":"word","word":"note","hasSynonym":false},{"type":"word","word":"of","hasSynonym":false},{"type":"word","word":"some","hasSynonym":false},{"type":"word","word":"salient","hasSynonym":false},{"type":"word","word":"point,","hasSynonym":false},{"type":"word","word":"and","hasSynonym":false},{"type":"word","word":"found","hasSynonym":false},{"type":"word","word":"that","hasSynonym":false},{"type":"word","word":"this","hasSynonym":false},{"type":"word","word":"was","hasSynonym":false},{"type":"word","word":"so.","hasSynonym":false},{"type":"word","word":"I","hasSynonym":false},{"type":"word","word":"would","hasSynonym":false},{"type":"word","word":"have","hasSynonym":false},{"type":"word","word":"liked","hasSynonym":false},{"type":"word","word":"to","hasSynonym":false},{"type":"word","word":"have","hasSynonym":false},{"type":"word","word":"asked","hasSynonym":false},{"type":"word","word":"the","hasSynonym":false},{"type":"word","word":"driver","hasSynonym":false},{"type":"word","word":"what","hasSynonym":false},{"type":"word","word":"this","hasSynonym":false},{"type":"word","word":"all","hasSynonym":false},{"type":"word","word":"meant,","hasSynonym":false},{"type":"word","word":"but","hasSynonym":false},{"type":"word","word":"I","hasSynonym":false},{"type":"word","word":"really","hasSynonym":false},{"type":"word","word":"feared","synonym":"scared, afraid","hasSynonym":true},{"type":"word","word":"to","hasSynonym":false},{"type":"word","word":"do","hasSynonym":false},{"type":"word","word":"so,","hasSynonym":false},{"type":"word","word":"for","hasSynonym":false},{"type":"word","word":"I","hasSynonym":false},{"type":"word","word":"thought","hasSynonym":false},{"type":"word","word":"that,","hasSynonym":false},{"type":"word","word":"placed","hasSynonym":false},{"type":"word","word":"as","hasSynonym":false},{"type":"word","word":"I","hasSynonym":false},{"type":"word","word":"was,","hasSynonym":false},{"type":"word","word":"any","hasSynonym":false},{"type":"word","word":"protest","hasSynonym":false},{"type":"word","word":"would","hasSynonym":false},{"type":"word","word":"have","hasSynonym":false},{"type":"word","word":"had","hasSynonym":false},{"type":"word","word":"no","hasSynonym":false},{"type":"word","word":"effect","hasSynonym":false},{"type":"word","word":"in","hasSynonym":false},{"type":"word","word":"case","hasSynonym":false},{"type":"word","word":"there","hasSynonym":false},{"type":"word","word":"had","hasSynonym":false},{"type":"word","word":"been","hasSynonym":false},{"type":"word","word":"an","hasSynonym":false},{"type":"word","word":"intention","hasSynonym":false},{"type":"word","word":"to","hasSynonym":false},{"type":"word","word":"delay.","synonym":"postpone, prolong","hasSynonym":true},{"type":"word","word":"By-and-by,","hasSynonym":false},{"type":"word","word":"however,","hasSynonym":false},{"type":"word","word":"as","hasSynonym":false},{"type":"word","word":"I","hasSynonym":false},{"type":"word","word":"was","hasSynonym":false},{"type":"word","word":"curious","hasSynonym":false},{"type":"word","word":"to","hasSynonym":false},{"type":"word","word":"know","hasSynonym":false},{"type":"word","word":"how","hasSynonym":false},{"type":"word","word":"time","hasSynonym":false},{"type":"word","word":"was","hasSynonym":false},{"type":"word","word":"passing,","hasSynonym":false},{"type":"word","word":"I","hasSynonym":false},{"type":"word","word":"struck","synonym":"surprised","hasSynonym":true},{"type":"word","word":"a","hasSynonym":false},{"type":"word","word":"match,","synonym":"stick with a tip having a chemical substance that produces fire when rubbed","hasSynonym":true},{"type":"word","word":"and","hasSynonym":false},{"type":"word","word":"by","hasSynonym":false},{"type":"word","word":"its","hasSynonym":false},{"type":"word","word":"flame","synonym":"fire, flare, blaze","hasSynonym":true},{"type":"word","word":"looked","hasSynonym":false},{"type":"word","word":"at","hasSynonym":false},{"type":"word","word":"my","hasSynonym":false},{"type":"word","word":"watch;","hasSynonym":false},{"type":"word","word":"it","hasSynonym":false},{"type":"word","word":"was","hasSynonym":false},{"type":"word","word":"within","hasSynonym":false},{"type":"word","word":"a","hasSynonym":false},{"type":"word","word":"few","hasSynonym":false},{"type":"word","word":"minutes","hasSynonym":false},{"type":"word","word":"of","hasSynonym":false},{"type":"word","word":"midnight.","hasSynonym":false},{"type":"word","word":"This","hasSynonym":false},{"type":"word","word":"gave","hasSynonym":false},{"type":"word","word":"me","hasSynonym":false},{"type":"word","word":"a","hasSynonym":false},{"type":"word","word":"sort","hasSynonym":false},{"type":"word","word":"of","hasSynonym":false},{"type":"word","word":"shock,","hasSynonym":false},{"type":"word","word":"for","hasSynonym":false},{"type":"word","word":"I","hasSynonym":false},{"type":"word","word":"suppose","hasSynonym":false},{"type":"word","word":"the","hasSynonym":false},{"type":"word","word":"general","hasSynonym":false},{"type":"word","word":"superstition","hasSynonym":false},{"type":"word","word":"about","hasSynonym":false},{"type":"word","word":"midnight","hasSynonym":false},{"type":"word","word":"was","hasSynonym":false},{"type":"word","word":"increased","hasSynonym":false},{"type":"word","word":"by","hasSynonym":false},{"type":"word","word":"my","hasSynonym":false},{"type":"word","word":"recent","hasSynonym":false},{"type":"word","word":"experiences.","hasSynonym":false},{"type":"word","word":"I","hasSynonym":false},{"type":"word","word":"waited","hasSynonym":false},{"type":"word","word":"with","hasSynonym":false},{"type":"word","word":"a","hasSynonym":false},{"type":"word","word":"sick","hasSynonym":false},{"type":"word","word":"feeling","hasSynonym":false},{"type":"word","word":"of","hasSynonym":false},{"type":"word","word":"suspense.","hasSynonym":false}],[{"type":"word","word":"Then","hasSynonym":false},{"type":"word","word":"a","hasSynonym":false},{"type":"word","word":"dog","hasSynonym":false},{"type":"word","word":"began","hasSynonym":false},{"type":"word","word":"to","hasSynonym":false},{"type":"word","word":"howl","synonym":"yelp, scream","hasSynonym":true},{"type":"word","word":"somewhere","hasSynonym":false},{"type":"word","word":"in","hasSynonym":false},{"type":"word","word":"a","hasSynonym":false},{"type":"word","word":"farmhouse","hasSynonym":false},{"type":"word","word":"far","hasSynonym":false},{"type":"word","word":"down","hasSynonym":false},{"type":"word","word":"the","hasSynonym":false},{"type":"word","word":"road","hasSynonym":false},{"type":"word","word":"—a","hasSynonym":false},{"type":"word","word":"long,","hasSynonym":false},{"type":"word","word":"agonised","synonym":"agonise, suffe","hasSynonym":true},{"type":"word","word":"wailing,","synonym":"scream","hasSynonym":true},{"type":"word","word":"as","hasSynonym":false},{"type":"word","word":"if","hasSynonym":false},{"type":"word","word":"from","hasSynonym":false},{"type":"word","word":"fear.","hasSynonym":false},{"type":"word","word":"The","hasSynonym":false},{"type":"word","word":"sound","hasSynonym":false},{"type":"word","word":"was","hasSynonym":false},{"type":"word","word":"taken","hasSynonym":false},{"type":"word","word":"up","hasSynonym":false},{"type":"word","word":"by","hasSynonym":false},{"type":"word","word":"another","hasSynonym":false},{"type":"word","word":"dog,","hasSynonym":false},{"type":"word","word":"and","hasSynonym":false},{"type":"word","word":"then","hasSynonym":false},{"type":"word","word":"another","hasSynonym":false},{"type":"word","word":"and","hasSynonym":false},{"type":"word","word":"another,","hasSynonym":false},{"type":"word","word":"till,","hasSynonym":false},{"type":"word","word":"borne","synonym":"carried by","hasSynonym":true},{"type":"word","word":"on","hasSynonym":false},{"type":"word","word":"the","hasSynonym":false},{"type":"word","word":"wind","hasSynonym":false},{"type":"word","word":"which","hasSynonym":false},{"type":"word","word":"now","hasSynonym":false},{"type":"word","word":"sighed","synonym":"deep breath","hasSynonym":true},{"type":"word","word":"softly","hasSynonym":false},{"type":"word","word":"through","hasSynonym":false},{"type":"word","word":"the","hasSynonym":false},{"type":"word","word":"Pass,","hasSynonym":false},{"type":"word","word":"a","hasSynonym":false},{"type":"word","word":"wild","hasSynonym":false},{"type":"word","word":"howling","synonym":"screaming","hasSynonym":true},{"type":"word","word":"began,","hasSynonym":false},{"type":"word","word":"which","hasSynonym":false},{"type":"word","word":"seemed","synonym":"appeared to be, looked to be","hasSynonym":true},{"type":"word","word":"to","hasSynonym":false},{"type":"word","word":"come","hasSynonym":false},{"type":"word","word":"from","hasSynonym":false},{"type":"word","word":"all","hasSynonym":false},{"type":"word","word":"over","hasSynonym":false},{"type":"word","word":"the","hasSynonym":false},{"type":"word","word":"country,","hasSynonym":false},{"type":"word","word":"as","hasSynonym":false},{"type":"word","word":"far","hasSynonym":false},{"type":"word","word":"as","hasSynonym":false},{"type":"word","word":"the","hasSynonym":false},{"type":"word","word":"imagination","hasSynonym":false},{"type":"word","word":"could","hasSynonym":false},{"type":"word","word":"grasp","synonym":"firm hold","hasSynonym":true},{"type":"word","word":"it","hasSynonym":false},{"type":"word","word":"through","hasSynonym":false},{"type":"word","word":"the","hasSynonym":false},{"type":"word","word":"gloom","synonym":"darkness, shadows","hasSynonym":true},{"type":"word","word":"of","hasSynonym":false},{"type":"word","word":"the","hasSynonym":false},{"type":"word","word":"night.","hasSynonym":false},{"type":"word","word":"At","hasSynonym":false},{"type":"word","word":"the","hasSynonym":false},{"type":"word","word":"first","hasSynonym":false},{"type":"word","word":"howl","synonym":"yelp, scream","hasSynonym":true},{"type":"word","word":"the","hasSynonym":false},{"type":"word","word":"horses","hasSynonym":false},{"type":"word","word":"began","hasSynonym":false},{"type":"word","word":"to","hasSynonym":false},{"type":"word","word":"strain","synonym":"wrench, twist, worry","hasSynonym":true},{"type":"word","word":"and","hasSynonym":false},{"type":"word","word":"rear,","hasSynonym":false},{"type":"word","word":"but","hasSynonym":false},{"type":"word","word":"the","hasSynonym":false},{"type":"word","word":"driver","hasSynonym":false},{"type":"word","word":"spoke","hasSynonym":false},{"type":"word","word":"to","hasSynonym":false},{"type":"word","word":"them","hasSynonym":false},{"type":"word","word":"soothingly,","synonym":"softly","hasSynonym":true},{"type":"word","word":"and","hasSynonym":false},{"type":"word","word":"they","hasSynonym":false},{"type":"word","word":"quieted","hasSynonym":false},{"type":"word","word":"down,","hasSynonym":false},{"type":"word","word":"but","hasSynonym":false},{"type":"word","word":"shivered","synonym":"trembled, shake","hasSynonym":true},{"type":"word","word":"and","hasSynonym":false},{"type":"word","word":"sweated","hasSynonym":false},{"type":"word","word":"as","hasSynonym":false},{"type":"word","word":"though","hasSynonym":false},{"type":"word","word":"after","hasSynonym":false},{"type":"word","word":"a","hasSynonym":false},{"type":"word","word":"runaway","hasSynonym":false},{"type":"word","word":"from","hasSynonym":false},{"type":"word","word":"sudden","hasSynonym":false},{"type":"word","word":"fright.","synonym":"fear","hasSynonym":true},{"type":"word","word":"Then,","hasSynonym":false},{"type":"word","word":"far","hasSynonym":false},{"type":"word","word":"off","hasSynonym":false},{"type":"word","word":"in","hasSynonym":false},{"type":"word","word":"the","hasSynonym":false},{"type":"word","word":"distance,","hasSynonym":false},{"type":"word","word":"from","hasSynonym":false},{"type":"word","word":"the","hasSynonym":false},{"type":"word","word":"mountains","hasSynonym":false},{"type":"word","word":"on","hasSynonym":false},{"type":"word","word":"each","hasSynonym":false},{"type":"word","word":"side","hasSynonym":false},{"type":"word","word":"of","hasSynonym":false},{"type":"word","word":"us","hasSynonym":false},{"type":"word","word":"began","hasSynonym":false},{"type":"word","word":"a","hasSynonym":false},{"type":"word","word":"louder","hasSynonym":false},{"type":"word","word":"and","hasSynonym":false},{"type":"word","word":"a","hasSynonym":false},{"type":"word","word":"sharper","hasSynonym":false},{"type":"word","word":"howling—that","synonym":"screaming","hasSynonym":true},{"type":"word","word":"of","hasSynonym":false},{"type":"word","word":"wolves—which","hasSynonym":false},{"type":"word","word":"affected","hasSynonym":false},{"type":"word","word":"both","hasSynonym":false},{"type":"word","word":"the","hasSynonym":false},{"type":"word","word":"horses","hasSynonym":false},{"type":"word","word":"and","hasSynonym":false},{"type":"word","word":"myself","hasSynonym":false},{"type":"word","word":"in","hasSynonym":false},{"type":"word","word":"the","hasSynonym":false},{"type":"word","word":"same","hasSynonym":false},{"type":"word","word":"way—for","hasSynonym":false},{"type":"word","word":"I","hasSynonym":false},{"type":"word","word":"was","hasSynonym":false},{"type":"word","word":"minded","hasSynonym":false},{"type":"word","word":"to","hasSynonym":false},{"type":"word","word":"jump","hasSynonym":false},{"type":"word","word":"from","hasSynonym":false},{"type":"word","word":"the","hasSynonym":false},{"type":"word","word":"calèche","hasSynonym":false},{"type":"word","word":"and","hasSynonym":false},{"type":"word","word":"run,","hasSynonym":false},{"type":"word","word":"whilst","synonym":"while","hasSynonym":true},{"type":"word","word":"they","hasSynonym":false},{"type":"word","word":"reared","synonym":"go back","hasSynonym":true},{"type":"word","word":"again","hasSynonym":false},{"type":"word","word":"and","hasSynonym":false},{"type":"word","word":"plunged","synonym":"pushed, thrust","hasSynonym":true},{"type":"word","word":"madly,","synonym":"crazily","hasSynonym":true},{"type":"word","word":"so","hasSynonym":false},{"type":"word","word":"that","hasSynonym":false},{"type":"word","word":"the","hasSynonym":false},{"type":"word","word":"driver","hasSynonym":false},{"type":"word","word":"had","hasSynonym":false},{"type":"word","word":"to","hasSynonym":false},{"type":"word","word":"use","hasSynonym":false},{"type":"word","word":"all","hasSynonym":false},{"type":"word","word":"his","hasSynonym":false},{"type":"word","word":"great","hasSynonym":false},{"type":"word","word":"strength","hasSynonym":false},{"type":"word","word":"to","hasSynonym":false},{"type":"word","word":"keep","hasSynonym":false},{"type":"word","word":"them","hasSynonym":false},{"type":"word","word":"from","hasSynonym":false},{"type":"word","word":"bolting.","synonym":"releasing","hasSynonym":true},{"type":"word","word":"In","hasSynonym":false},{"type":"word","word":"a","hasSynonym":false},{"type":"word","word":"few","hasSynonym":false},{"type":"word","word":"minutes,","hasSynonym":false},{"type":"word","word":"however,","hasSynonym":false},{"type":"word","word":"my","hasSynonym":false},{"type":"word","word":"own","hasSynonym":false},{"type":"word","word":"ears","hasSynonym":false},{"type":"word","word":"got","hasSynonym":false},{"type":"word","word":"accustomed","synonym":"usual, regular","hasSynonym":true},{"type":"word","word":"to","hasSynonym":false},{"type":"word","word":"the","hasSynonym":false},{"type":"word","word":"sound,","hasSynonym":false},{"type":"word","word":"and","hasSynonym":false},{"type":"word","word":"the","hasSynonym":false},{"type":"word","word":"horses","hasSynonym":false},{"type":"word","word":"so","hasSynonym":false},{"type":"word","word":"far","hasSynonym":false},{"type":"word","word":"became","hasSynonym":false},{"type":"word","word":"quiet","hasSynonym":false},{"type":"word","word":"that","hasSynonym":false},{"type":"word","word":"the","hasSynonym":false},{"type":"word","word":"driver","hasSynonym":false},{"type":"word","word":"was","hasSynonym":false},{"type":"word","word":"able","hasSynonym":false},{"type":"word","word":"to","hasSynonym":false},{"type":"word","word":"descend","hasSynonym":false},{"type":"word","word":"and","hasSynonym":false},{"type":"word","word":"to","hasSynonym":false},{"type":"word","word":"stand","hasSynonym":false},{"type":"word","word":"before","hasSynonym":false},{"type":"word","word":"them.","hasSynonym":false},{"type":"word","word":"He","hasSynonym":false},{"type":"word","word":"petted","synonym":"stroked","hasSynonym":true},{"type":"word","word":"and","hasSynonym":false},{"type":"word","word":"soothed","hasSynonym":false},{"type":"word","word":"them,","hasSynonym":false},{"type":"word","word":"and","hasSynonym":false},{"type":"word","word":"whispered","hasSynonym":false},{"type":"word","word":"something","hasSynonym":false},{"type":"word","word":"in","hasSynonym":false},{"type":"word","word":"their","hasSynonym":false},{"type":"word","word":"ears,","hasSynonym":false},{"type":"word","word":"as","hasSynonym":false},{"type":"word","word":"I","hasSynonym":false},{"type":"word","word":"have","hasSynonym":false},{"type":"word","word":"heard","hasSynonym":false},{"type":"word","word":"of","hasSynonym":false},{"type":"word","word":"horse-tamers","hasSynonym":false},{"type":"word","word":"doing,","hasSynonym":false},{"type":"word","word":"and","hasSynonym":false},{"type":"word","word":"with","hasSynonym":false},{"type":"word","word":"extraordinary","hasSynonym":false},{"type":"word","word":"effect,","hasSynonym":false},{"type":"word","word":"for","hasSynonym":false},{"type":"word","word":"under","hasSynonym":false},{"type":"word","word":"his","hasSynonym":false},{"type":"word","word":"caresses","synonym":"rub, touch","hasSynonym":true},{"type":"word","word":"they","hasSynonym":false},{"type":"word","word":"became","hasSynonym":false},{"type":"word","word":"quite","hasSynonym":false},{"type":"word","word":"manageable","synonym":"controllable","hasSynonym":true},{"type":"word","word":"again,","hasSynonym":false},{"type":"word","word":"though","hasSynonym":false},{"type":"word","word":"they","hasSynonym":false},{"type":"word","word":"still","hasSynonym":false},{"type":"word","word":"trembled.","synonym":"shake, vibrate","hasSynonym":true},{"type":"word","word":"The","hasSynonym":false},{"type":"word","word":"driver","hasSynonym":false},{"type":"word","word":"again","hasSynonym":false},{"type":"word","word":"took","hasSynonym":false},{"type":"word","word":"his","hasSynonym":false},{"type":"word","word":"seat,","hasSynonym":false},{"type":"word","word":"and","hasSynonym":false},{"type":"word","word":"shaking","hasSynonym":false},{"type":"word","word":"his","hasSynonym":false},{"type":"word","word":"reins,","hasSynonym":false},{"type":"word","word":"started","hasSynonym":false},{"type":"word","word":"off","hasSynonym":false},{"type":"word","word":"at","hasSynonym":false},{"type":"word","word":"a","hasSynonym":false},{"type":"word","word":"great","hasSynonym":false},{"type":"word","word":"pace.","hasSynonym":false},{"type":"word","word":"This","hasSynonym":false},{"type":"word","word":"time,","hasSynonym":false},{"type":"word","word":"after","hasSynonym":false},{"type":"word","word":"going","hasSynonym":false},{"type":"word","word":"to","hasSynonym":false},{"type":"word","word":"the","hasSynonym":false},{"type":"word","word":"far","hasSynonym":false},{"type":"word","word":"side","hasSynonym":false},{"type":"word","word":"of","hasSynonym":false},{"type":"word","word":"the","hasSynonym":false},{"type":"word","word":"Pass,","hasSynonym":false},{"type":"word","word":"he","hasSynonym":false},{"type":"word","word":"suddenly","hasSynonym":false},{"type":"word","word":"turned","hasSynonym":false},{"type":"word","word":"down","hasSynonym":false},{"type":"word","word":"a","hasSynonym":false},{"type":"word","word":"narrow","hasSynonym":false},{"type":"word","word":"roadway","hasSynonym":false},{"type":"word","word":"which","hasSynonym":false},{"type":"word","word":"ran","hasSynonym":false},{"type":"word","word":"sharply","hasSynonym":false},{"type":"word","word":"to","hasSynonym":false},{"type":"word","word":"the","hasSynonym":false},{"type":"word","word":"right.","hasSynonym":false}]]